Pypable/LICENSE
Pypable/__init__.py
Pypable/printers.py
Pypable/text.py
Pypable/mixins/__init__.py
Pypable/mixins/pipable.py
Pypable/utilities/__init__.py
Pypable/utilities/typing.py
pypable-1.0.1.dist-info/METADATA
pypable-1.0.1.dist-info/WHEEL
pypable-1.0.1.dist-info/licenses/LICENSE
pypable-1.0.1.dist-info/RECORD
