Metadata-Version: 2.3
Name: Pypable
Version: 1.0.1
Summary: A toolset for piping values between functions, with optional shell-like text-processing tools.
Project-URL: Homepage, https://github.com/faelin/Pypable
Project-URL: Issues, https://github.com/faelin/Pypable/issues
Author-email: Faelin <faelin.codes@gmail.com>
License-File: LICENSE
Classifier: License :: OSI Approved :: MIT License
Classifier: Operating System :: OS Independent
Classifier: Programming Language :: Python :: 3
Requires-Python: >=3.7
